trustlint/__init__.py
trustlint/index.ts
trustlint-1.0.3.dist-info/METADATA
trustlint-1.0.3.dist-info/WHEEL
trustlint-1.0.3.dist-info/top_level.txt
trustlint-1.0.3.dist-info/RECORD
