Metadata-Version: 2.4
Name: trustlint
Version: 1.0.3
Requires-Python: >=3.7
Dynamic: description
Dynamic: description-content-type
Dynamic: requires-python
